README.rst
setup.py
frate/__init__.py
frate/frate.py
frate.egg-info/PKG-INFO
frate.egg-info/SOURCES.txt
frate.egg-info/dependency_links.txt
frate.egg-info/entry_points.txt
frate.egg-info/top_level.txt