Metadata-Version: 1.0
Name: frate
Version: 0.2
Summary: Show file growing rate in real time
Home-page: https://github.com/pdrb/frate
Author: Pedro Buteri Gonring
Author-email: pedro@bigode.net
License: MIT
Keywords: file rate growing line lines filerate frate
Platform: UNKNOWN
